gdlib/__init__.py
gdlib-0.0.0.dist-info/LICENSE
gdlib-0.0.0.dist-info/METADATA
gdlib-0.0.0.dist-info/WHEEL
gdlib-0.0.0.dist-info/top_level.txt
gdlib-0.0.0.dist-info/RECORD
